.travis.yml
CHANGES.txt
MANIFEST.in
README.txt
bootstrap.py
buildout.cfg
setup.py
src/z3c/__init__.py
src/z3c.zrtresource.egg-info/PKG-INFO
src/z3c.zrtresource.egg-info/SOURCES.txt
src/z3c.zrtresource.egg-info/dependency_links.txt
src/z3c.zrtresource.egg-info/namespace_packages.txt
src/z3c.zrtresource.egg-info/not-zip-safe
src/z3c.zrtresource.egg-info/requires.txt
src/z3c.zrtresource.egg-info/top_level.txt
src/z3c/zrtresource/README.txt
src/z3c/zrtresource/__init__.py
src/z3c/zrtresource/configure.zcml
src/z3c/zrtresource/interfaces.py
src/z3c/zrtresource/meta.zcml
src/z3c/zrtresource/processor.py
src/z3c/zrtresource/replace.py
src/z3c/zrtresource/tests.py
src/z3c/zrtresource/zcml.py
src/z3c/zrtresource/zcml.txt
src/z3c/zrtresource/zrtresource.py